geotessera/__init__.py
geotessera/cli.py
geotessera/core.py
geotessera/country.py
geotessera/progress.py
geotessera/registry.py
geotessera/registry_cli.py
geotessera/tiles.py
geotessera/visualization.py
geotessera/web.py
geotessera-0.7.0.dist-info/licenses/LICENSE.md
geotessera-0.7.0.dist-info/METADATA
geotessera-0.7.0.dist-info/WHEEL
geotessera-0.7.0.dist-info/entry_points.txt
geotessera-0.7.0.dist-info/top_level.txt
geotessera-0.7.0.dist-info/RECORD
