Metadata-Version: 2.4
Name: geotessera
Version: 0.7.0
Summary: Python library interface to the Tessera geofoundation model embeddings
License: ISC License
Project-URL: Homepage, https://github.com/ucam-eo/geotessera
Project-URL: Documentation, https://geotessera.readthedocs.io
Project-URL: Repository, https://github.com/ucam-eo/geotessera
Project-URL: Issues, https://github.com/ucam-eo/geotessera/issues
Project-URL: Changelog, https://github.com/ucam-eo/geotessera/blob/main/CHANGES.md
Classifier: Development Status :: 3 - Alpha
Classifier: Intended Audience :: Developers
Classifier: Intended Audience :: Science/Research
Classifier: License :: OSI Approved :: ISC License (ISCL)
Classifier: Programming Language :: Python
Classifier: Programming Language :: Python :: 3
Classifier: Programming Language :: Python :: 3.11
Classifier: Programming Language :: Python :: 3.12
Classifier: Topic :: Scientific/Engineering :: GIS
Classifier: Topic :: Software Development :: Libraries :: Python Modules
Classifier: Environment :: Console
Classifier: Operating System :: OS Independent
Requires-Python: >=3.11
License-File: LICENSE.md
Requires-Dist: numpy>=1.24.0
Requires-Dist: geopandas
Requires-Dist: pandas
Requires-Dist: matplotlib
Requires-Dist: rasterio
Requires-Dist: sphinx>=8.2.3
Requires-Dist: rich
Requires-Dist: typer
Requires-Dist: geodatasets>=2024.8.0
Requires-Dist: scikit-learn>=1.7.1
Requires-Dist: scikit-image>=0.25.2
Requires-Dist: pyarrow>=17.0.0
Requires-Dist: cram>=0.7
Dynamic: license-file
